Metadata-Version: 1.1
Name: ps_alchemy
Version: 0.0.7
Summary: SQLAlchemy provider for pyramid_sacrud.
Home-page: http://github.com/sacrud/ps_alchemy/
Author: Svintsov Dmitry
Author-email: sacrud@uralbash.ru
License: MIT
Platform: UNKNOWN
Classifier: Development Status :: 5 - Production/Stable
Classifier: Environment :: Web Environment
Classifier: Intended Audience :: Developers
Classifier: License :: OSI Approved :: MIT License
Classifier: Operating System :: OS Independent
Classifier: Programming Language :: Python
Classifier: Programming Language :: Python :: 2.7
Classifier: Programming Language :: Python :: 3
Classifier: Programming Language :: Python :: 3.3
Classifier: Programming Language :: Python :: 3.4
Classifier: Programming Language :: Python :: 3.5
Classifier: Framework :: Pyramid 
Classifier: Topic :: Internet
Classifier: Topic :: Database
